{"nodes": [{"id": "c_users_savet_creatrbase_v2_client_src_pages_community_community_jsx", "label": "Community.jsx", "file_type": "code", "source_file": "C:\\Users\\savet\\creatrbase-v2\\client\\src\\pages\\Community\\Community.jsx", "source_location": "L1"}, {"id": "community_votebutton", "label": "VoteButton()", "file_type": "code", "source_file": "C:\\Users\\savet\\creatrbase-v2\\client\\src\\pages\\Community\\Community.jsx", "source_location": "L19"}, {"id": "community_suggestioncard", "label": "SuggestionCard()", "file_type": "code", "source_file": "C:\\Users\\savet\\creatrbase-v2\\client\\src\\pages\\Community\\Community.jsx", "source_location": "L39"}, {"id": "community_suggestmodal", "label": "SuggestModal()", "file_type": "code", "source_file": "C:\\Users\\savet\\creatrbase-v2\\client\\src\\pages\\Community\\Community.jsx", "source_location": "L92"}, {"id": "community_community", "label": "Community()", "file_type": "code", "source_file": "C:\\Users\\savet\\creatrbase-v2\\client\\src\\pages\\Community\\Community.jsx", "source_location": "L184"}], "edges": [{"source": "c_users_savet_creatrbase_v2_client_src_pages_community_community_jsx", "target": "react", "relation": "imports_from", "confidence": "EXTRACTED", "source_file": "C:\\Users\\savet\\creatrbase-v2\\client\\src\\pages\\Community\\Community.jsx", "source_location": "L1", "weight": 1.0}, {"source": "c_users_savet_creatrbase_v2_client_src_pages_community_community_jsx", "target": "c_users_savet_creatrbase_v2_client_src_layouts_applayout_applayout", "relation": "imports_from", "confidence": "EXTRACTED", "source_file": "C:\\Users\\savet\\creatrbase-v2\\client\\src\\pages\\Community\\Community.jsx", "source_location": "L2", "weight": 1.0}, {"source": "c_users_savet_creatrbase_v2_client_src_pages_community_community_jsx", "target": "c_users_savet_creatrbase_v2_client_src_components_upgradegate_upgradegate", "relation": "imports_from", "confidence": "EXTRACTED", "source_file": "C:\\Users\\savet\\creatrbase-v2\\client\\src\\pages\\Community\\Community.jsx", "source_location": "L3", "weight": 1.0}, {"source": "c_users_savet_creatrbase_v2_client_src_pages_community_community_jsx", "target": "c_users_savet_creatrbase_v2_client_src_lib_api", "relation": "imports_from", "confidence": "EXTRACTED", "source_file": "C:\\Users\\savet\\creatrbase-v2\\client\\src\\pages\\Community\\Community.jsx", "source_location": "L4", "weight": 1.0}, {"source": "c_users_savet_creatrbase_v2_client_src_pages_community_community_jsx", "target": "c_users_savet_creatrbase_v2_client_src_pages_community_community_module_css", "relation": "imports_from", "confidence": "EXTRACTED", "source_file": "C:\\Users\\savet\\creatrbase-v2\\client\\src\\pages\\Community\\Community.jsx", "source_location": "L5", "weight": 1.0}, {"source": "c_users_savet_creatrbase_v2_client_src_pages_community_community_jsx", "target": "community_votebutton", "relation": "contains", "confidence": "EXTRACTED", "source_file": "C:\\Users\\savet\\creatrbase-v2\\client\\src\\pages\\Community\\Community.jsx", "source_location": "L19", "weight": 1.0}, {"source": "c_users_savet_creatrbase_v2_client_src_pages_community_community_jsx", "target": "community_suggestioncard", "relation": "contains", "confidence": "EXTRACTED", "source_file": "C:\\Users\\savet\\creatrbase-v2\\client\\src\\pages\\Community\\Community.jsx", "source_location": "L39", "weight": 1.0}, {"source": "c_users_savet_creatrbase_v2_client_src_pages_community_community_jsx", "target": "community_suggestmodal", "relation": "contains", "confidence": "EXTRACTED", "source_file": "C:\\Users\\savet\\creatrbase-v2\\client\\src\\pages\\Community\\Community.jsx", "source_location": "L92", "weight": 1.0}, {"source": "c_users_savet_creatrbase_v2_client_src_pages_community_community_jsx", "target": "community_community", "relation": "contains", "confidence": "EXTRACTED", "source_file": "C:\\Users\\savet\\creatrbase-v2\\client\\src\\pages\\Community\\Community.jsx", "source_location": "L184", "weight": 1.0}], "raw_calls": [{"caller_nid": "community_suggestioncard", "callee": "useState", "source_file": "C:\\Users\\savet\\creatrbase-v2\\client\\src\\pages\\Community\\Community.jsx", "source_location": "L40"}, {"caller_nid": "community_suggestmodal", "callee": "useState", "source_file": "C:\\Users\\savet\\creatrbase-v2\\client\\src\\pages\\Community\\Community.jsx", "source_location": "L93"}, {"caller_nid": "community_suggestmodal", "callee": "useState", "source_file": "C:\\Users\\savet\\creatrbase-v2\\client\\src\\pages\\Community\\Community.jsx", "source_location": "L94"}, {"caller_nid": "community_suggestmodal", "callee": "useState", "source_file": "C:\\Users\\savet\\creatrbase-v2\\client\\src\\pages\\Community\\Community.jsx", "source_location": "L95"}, {"caller_nid": "community_suggestmodal", "callee": "useState", "source_file": "C:\\Users\\savet\\creatrbase-v2\\client\\src\\pages\\Community\\Community.jsx", "source_location": "L96"}, {"caller_nid": "community_suggestmodal", "callee": "useState", "source_file": "C:\\Users\\savet\\creatrbase-v2\\client\\src\\pages\\Community\\Community.jsx", "source_location": "L97"}, {"caller_nid": "community_suggestmodal", "callee": "useRef", "source_file": "C:\\Users\\savet\\creatrbase-v2\\client\\src\\pages\\Community\\Community.jsx", "source_location": "L98"}, {"caller_nid": "community_suggestmodal", "callee": "useEffect", "source_file": "C:\\Users\\savet\\creatrbase-v2\\client\\src\\pages\\Community\\Community.jsx", "source_location": "L100"}, {"caller_nid": "community_suggestmodal", "callee": "map", "source_file": "C:\\Users\\savet\\creatrbase-v2\\client\\src\\pages\\Community\\Community.jsx", "source_location": "L166"}, {"caller_nid": "community_suggestmodal", "callee": "trim", "source_file": "C:\\Users\\savet\\creatrbase-v2\\client\\src\\pages\\Community\\Community.jsx", "source_location": "L174"}, {"caller_nid": "community_community", "callee": "useState", "source_file": "C:\\Users\\savet\\creatrbase-v2\\client\\src\\pages\\Community\\Community.jsx", "source_location": "L185"}, {"caller_nid": "community_community", "callee": "useState", "source_file": "C:\\Users\\savet\\creatrbase-v2\\client\\src\\pages\\Community\\Community.jsx", "source_location": "L186"}, {"caller_nid": "community_community", "callee": "useState", "source_file": "C:\\Users\\savet\\creatrbase-v2\\client\\src\\pages\\Community\\Community.jsx", "source_location": "L187"}, {"caller_nid": "community_community", "callee": "useState", "source_file": "C:\\Users\\savet\\creatrbase-v2\\client\\src\\pages\\Community\\Community.jsx", "source_location": "L188"}, {"caller_nid": "community_community", "callee": "useState", "source_file": "C:\\Users\\savet\\creatrbase-v2\\client\\src\\pages\\Community\\Community.jsx", "source_location": "L189"}, {"caller_nid": "community_community", "callee": "useState", "source_file": "C:\\Users\\savet\\creatrbase-v2\\client\\src\\pages\\Community\\Community.jsx", "source_location": "L190"}, {"caller_nid": "community_community", "callee": "useState", "source_file": "C:\\Users\\savet\\creatrbase-v2\\client\\src\\pages\\Community\\Community.jsx", "source_location": "L191"}, {"caller_nid": "community_community", "callee": "useState", "source_file": "C:\\Users\\savet\\creatrbase-v2\\client\\src\\pages\\Community\\Community.jsx", "source_location": "L192"}, {"caller_nid": "community_community", "callee": "useState", "source_file": "C:\\Users\\savet\\creatrbase-v2\\client\\src\\pages\\Community\\Community.jsx", "source_location": "L193"}, {"caller_nid": "community_community", "callee": "useState", "source_file": "C:\\Users\\savet\\creatrbase-v2\\client\\src\\pages\\Community\\Community.jsx", "source_location": "L194"}, {"caller_nid": "community_community", "callee": "useState", "source_file": "C:\\Users\\savet\\creatrbase-v2\\client\\src\\pages\\Community\\Community.jsx", "source_location": "L195"}, {"caller_nid": "community_community", "callee": "useState", "source_file": "C:\\Users\\savet\\creatrbase-v2\\client\\src\\pages\\Community\\Community.jsx", "source_location": "L196"}, {"caller_nid": "community_community", "callee": "useEffect", "source_file": "C:\\Users\\savet\\creatrbase-v2\\client\\src\\pages\\Community\\Community.jsx", "source_location": "L198"}, {"caller_nid": "community_community", "callee": "useEffect", "source_file": "C:\\Users\\savet\\creatrbase-v2\\client\\src\\pages\\Community\\Community.jsx", "source_location": "L204"}, {"caller_nid": "community_community", "callee": "map", "source_file": "C:\\Users\\savet\\creatrbase-v2\\client\\src\\pages\\Community\\Community.jsx", "source_location": "L303"}, {"caller_nid": "community_community", "callee": "map", "source_file": "C:\\Users\\savet\\creatrbase-v2\\client\\src\\pages\\Community\\Community.jsx", "source_location": "L320"}, {"caller_nid": "community_community", "callee": "map", "source_file": "C:\\Users\\savet\\creatrbase-v2\\client\\src\\pages\\Community\\Community.jsx", "source_location": "L330"}, {"caller_nid": "community_community", "callee": "map", "source_file": "C:\\Users\\savet\\creatrbase-v2\\client\\src\\pages\\Community\\Community.jsx", "source_location": "L353"}]}