{"nodes": [{"id": "src_domains_gmail_gmailroutes_js", "label": "gmailRoutes.js", "file_type": "code", "source_file": "src\\domains\\gmail\\gmailRoutes.js", "source_location": "L1"}, {"id": "gmailroutes_resolvecreator", "label": "resolveCreator()", "file_type": "code", "source_file": "src\\domains\\gmail\\gmailRoutes.js", "source_location": "L33"}, {"id": "gmailroutes_getfreshtoken", "label": "getFreshToken()", "file_type": "code", "source_file": "src\\domains\\gmail\\gmailRoutes.js", "source_location": "L43"}, {"id": "gmailroutes_gmailroutes", "label": "gmailRoutes()", "file_type": "code", "source_file": "src\\domains\\gmail\\gmailRoutes.js", "source_location": "L66"}], "edges": [{"source": "src_domains_gmail_gmailroutes_js", "target": "gmailroutes_resolvecreator", "relation": "contains", "confidence": "EXTRACTED", "source_file": "src\\domains\\gmail\\gmailRoutes.js", "source_location": "L33", "weight": 1.0}, {"source": "src_domains_gmail_gmailroutes_js", "target": "gmailroutes_getfreshtoken", "relation": "contains", "confidence": "EXTRACTED", "source_file": "src\\domains\\gmail\\gmailRoutes.js", "source_location": "L43", "weight": 1.0}, {"source": "src_domains_gmail_gmailroutes_js", "target": "gmailroutes_gmailroutes", "relation": "contains", "confidence": "EXTRACTED", "source_file": "src\\domains\\gmail\\gmailRoutes.js", "source_location": "L66", "weight": 1.0}], "raw_calls": [{"caller_nid": "gmailroutes_resolvecreator", "callee": "getPrisma", "source_file": "src\\domains\\gmail\\gmailRoutes.js", "source_location": "L34"}, {"caller_nid": "gmailroutes_resolvecreator", "callee": "findFirst", "source_file": "src\\domains\\gmail\\gmailRoutes.js", "source_location": "L35"}, {"caller_nid": "gmailroutes_getfreshtoken", "callee": "getPrisma", "source_file": "src\\domains\\gmail\\gmailRoutes.js", "source_location": "L44"}, {"caller_nid": "gmailroutes_getfreshtoken", "callee": "getTime", "source_file": "src\\domains\\gmail\\gmailRoutes.js", "source_location": "L47"}, {"caller_nid": "gmailroutes_getfreshtoken", "callee": "now", "source_file": "src\\domains\\gmail\\gmailRoutes.js", "source_location": "L47"}, {"caller_nid": "gmailroutes_getfreshtoken", "callee": "decrypt", "source_file": "src\\domains\\gmail\\gmailRoutes.js", "source_location": "L49"}, {"caller_nid": "gmailroutes_getfreshtoken", "callee": "refreshGmailToken", "source_file": "src\\domains\\gmail\\gmailRoutes.js", "source_location": "L53"}, {"caller_nid": "gmailroutes_getfreshtoken", "callee": "decrypt", "source_file": "src\\domains\\gmail\\gmailRoutes.js", "source_location": "L53"}, {"caller_nid": "gmailroutes_getfreshtoken", "callee": "update", "source_file": "src\\domains\\gmail\\gmailRoutes.js", "source_location": "L54"}, {"caller_nid": "gmailroutes_getfreshtoken", "callee": "encrypt", "source_file": "src\\domains\\gmail\\gmailRoutes.js", "source_location": "L57"}, {"caller_nid": "gmailroutes_gmailroutes", "callee": "get", "source_file": "src\\domains\\gmail\\gmailRoutes.js", "source_location": "L70"}, {"caller_nid": "gmailroutes_gmailroutes", "callee": "get", "source_file": "src\\domains\\gmail\\gmailRoutes.js", "source_location": "L87"}, {"caller_nid": "gmailroutes_gmailroutes", "callee": "get", "source_file": "src\\domains\\gmail\\gmailRoutes.js", "source_location": "L170"}, {"caller_nid": "gmailroutes_gmailroutes", "callee": "delete", "source_file": "src\\domains\\gmail\\gmailRoutes.js", "source_location": "L187"}, {"caller_nid": "gmailroutes_gmailroutes", "callee": "post", "source_file": "src\\domains\\gmail\\gmailRoutes.js", "source_location": "L200"}]}