{"nodes": [{"id": "c_users_savet_creatrbase_v2_client_src_pages_toolkit_toolkit_jsx", "label": "Toolkit.jsx", "file_type": "code", "source_file": "C:\\Users\\savet\\creatrbase-v2\\client\\src\\pages\\Toolkit\\Toolkit.jsx", "source_location": "L1"}, {"id": "toolkit_tagssection", "label": "TagsSection()", "file_type": "code", "source_file": "C:\\Users\\savet\\creatrbase-v2\\client\\src\\pages\\Toolkit\\Toolkit.jsx", "source_location": "L12"}, {"id": "toolkit_toolkit", "label": "Toolkit()", "file_type": "code", "source_file": "C:\\Users\\savet\\creatrbase-v2\\client\\src\\pages\\Toolkit\\Toolkit.jsx", "source_location": "L148"}], "edges": [{"source": "c_users_savet_creatrbase_v2_client_src_pages_toolkit_toolkit_jsx", "target": "react", "relation": "imports_from", "confidence": "EXTRACTED", "source_file": "C:\\Users\\savet\\creatrbase-v2\\client\\src\\pages\\Toolkit\\Toolkit.jsx", "source_location": "L1", "weight": 1.0}, {"source": "c_users_savet_creatrbase_v2_client_src_pages_toolkit_toolkit_jsx", "target": "c_users_savet_creatrbase_v2_client_src_layouts_applayout_applayout", "relation": "imports_from", "confidence": "EXTRACTED", "source_file": "C:\\Users\\savet\\creatrbase-v2\\client\\src\\pages\\Toolkit\\Toolkit.jsx", "source_location": "L2", "weight": 1.0}, {"source": "c_users_savet_creatrbase_v2_client_src_pages_toolkit_toolkit_jsx", "target": "c_users_savet_creatrbase_v2_client_src_lib_api", "relation": "imports_from", "confidence": "EXTRACTED", "source_file": "C:\\Users\\savet\\creatrbase-v2\\client\\src\\pages\\Toolkit\\Toolkit.jsx", "source_location": "L3", "weight": 1.0}, {"source": "c_users_savet_creatrbase_v2_client_src_pages_toolkit_toolkit_jsx", "target": "c_users_savet_creatrbase_v2_client_src_pages_toolkit_toolkit_module_css", "relation": "imports_from", "confidence": "EXTRACTED", "source_file": "C:\\Users\\savet\\creatrbase-v2\\client\\src\\pages\\Toolkit\\Toolkit.jsx", "source_location": "L4", "weight": 1.0}, {"source": "c_users_savet_creatrbase_v2_client_src_pages_toolkit_toolkit_jsx", "target": "toolkit_tagssection", "relation": "contains", "confidence": "EXTRACTED", "source_file": "C:\\Users\\savet\\creatrbase-v2\\client\\src\\pages\\Toolkit\\Toolkit.jsx", "source_location": "L12", "weight": 1.0}, {"source": "c_users_savet_creatrbase_v2_client_src_pages_toolkit_toolkit_jsx", "target": "toolkit_toolkit", "relation": "contains", "confidence": "EXTRACTED", "source_file": "C:\\Users\\savet\\creatrbase-v2\\client\\src\\pages\\Toolkit\\Toolkit.jsx", "source_location": "L148", "weight": 1.0}], "raw_calls": [{"caller_nid": "toolkit_tagssection", "callee": "useState", "source_file": "C:\\Users\\savet\\creatrbase-v2\\client\\src\\pages\\Toolkit\\Toolkit.jsx", "source_location": "L13"}, {"caller_nid": "toolkit_tagssection", "callee": "useState", "source_file": "C:\\Users\\savet\\creatrbase-v2\\client\\src\\pages\\Toolkit\\Toolkit.jsx", "source_location": "L14"}, {"caller_nid": "toolkit_tagssection", "callee": "useState", "source_file": "C:\\Users\\savet\\creatrbase-v2\\client\\src\\pages\\Toolkit\\Toolkit.jsx", "source_location": "L15"}, {"caller_nid": "toolkit_tagssection", "callee": "useState", "source_file": "C:\\Users\\savet\\creatrbase-v2\\client\\src\\pages\\Toolkit\\Toolkit.jsx", "source_location": "L16"}, {"caller_nid": "toolkit_tagssection", "callee": "useState", "source_file": "C:\\Users\\savet\\creatrbase-v2\\client\\src\\pages\\Toolkit\\Toolkit.jsx", "source_location": "L17"}, {"caller_nid": "toolkit_tagssection", "callee": "useEffect", "source_file": "C:\\Users\\savet\\creatrbase-v2\\client\\src\\pages\\Toolkit\\Toolkit.jsx", "source_location": "L19"}, {"caller_nid": "toolkit_tagssection", "callee": "useEffect", "source_file": "C:\\Users\\savet\\creatrbase-v2\\client\\src\\pages\\Toolkit\\Toolkit.jsx", "source_location": "L23"}, {"caller_nid": "toolkit_tagssection", "callee": "map", "source_file": "C:\\Users\\savet\\creatrbase-v2\\client\\src\\pages\\Toolkit\\Toolkit.jsx", "source_location": "L82"}, {"caller_nid": "toolkit_tagssection", "callee": "trim", "source_file": "C:\\Users\\savet\\creatrbase-v2\\client\\src\\pages\\Toolkit\\Toolkit.jsx", "source_location": "L98"}, {"caller_nid": "toolkit_tagssection", "callee": "map", "source_file": "C:\\Users\\savet\\creatrbase-v2\\client\\src\\pages\\Toolkit\\Toolkit.jsx", "source_location": "L112"}]}