{"nodes": [{"id": "c_users_savet_creatrbase_v2_src_domains_auth_authroutes_js", "label": "authRoutes.js", "file_type": "code", "source_file": "C:\\Users\\savet\\creatrbase-v2\\src\\domains\\auth\\authRoutes.js", "source_location": "L1"}, {"id": "authroutes_setsessioncookie", "label": "setSessionCookie()", "file_type": "code", "source_file": "C:\\Users\\savet\\creatrbase-v2\\src\\domains\\auth\\authRoutes.js", "source_location": "L14"}, {"id": "authroutes_authroutes", "label": "authRoutes()", "file_type": "code", "source_file": "C:\\Users\\savet\\creatrbase-v2\\src\\domains\\auth\\authRoutes.js", "source_location": "L20"}], "edges": [{"source": "c_users_savet_creatrbase_v2_src_domains_auth_authroutes_js", "target": "authroutes_setsessioncookie", "relation": "contains", "confidence": "EXTRACTED", "source_file": "C:\\Users\\savet\\creatrbase-v2\\src\\domains\\auth\\authRoutes.js", "source_location": "L14", "weight": 1.0}, {"source": "c_users_savet_creatrbase_v2_src_domains_auth_authroutes_js", "target": "authroutes_authroutes", "relation": "contains", "confidence": "EXTRACTED", "source_file": "C:\\Users\\savet\\creatrbase-v2\\src\\domains\\auth\\authRoutes.js", "source_location": "L20", "weight": 1.0}], "raw_calls": [{"caller_nid": "authroutes_setsessioncookie", "callee": "sign", "source_file": "C:\\Users\\savet\\creatrbase-v2\\src\\domains\\auth\\authRoutes.js", "source_location": "L15"}, {"caller_nid": "authroutes_setsessioncookie", "callee": "setCookie", "source_file": "C:\\Users\\savet\\creatrbase-v2\\src\\domains\\auth\\authRoutes.js", "source_location": "L16"}, {"caller_nid": "authroutes_authroutes", "callee": "post", "source_file": "C:\\Users\\savet\\creatrbase-v2\\src\\domains\\auth\\authRoutes.js", "source_location": "L22"}, {"caller_nid": "authroutes_authroutes", "callee": "post", "source_file": "C:\\Users\\savet\\creatrbase-v2\\src\\domains\\auth\\authRoutes.js", "source_location": "L51"}, {"caller_nid": "authroutes_authroutes", "callee": "post", "source_file": "C:\\Users\\savet\\creatrbase-v2\\src\\domains\\auth\\authRoutes.js", "source_location": "L78"}, {"caller_nid": "authroutes_authroutes", "callee": "require", "source_file": "C:\\Users\\savet\\creatrbase-v2\\src\\domains\\auth\\authRoutes.js", "source_location": "L90"}, {"caller_nid": "authroutes_authroutes", "callee": "require", "source_file": "C:\\Users\\savet\\creatrbase-v2\\src\\domains\\auth\\authRoutes.js", "source_location": "L91"}, {"caller_nid": "authroutes_authroutes", "callee": "require", "source_file": "C:\\Users\\savet\\creatrbase-v2\\src\\domains\\auth\\authRoutes.js", "source_location": "L92"}, {"caller_nid": "authroutes_authroutes", "callee": "get", "source_file": "C:\\Users\\savet\\creatrbase-v2\\src\\domains\\auth\\authRoutes.js", "source_location": "L94"}, {"caller_nid": "authroutes_authroutes", "callee": "require", "source_file": "C:\\Users\\savet\\creatrbase-v2\\src\\domains\\auth\\authRoutes.js", "source_location": "L136"}, {"caller_nid": "authroutes_authroutes", "callee": "register", "source_file": "C:\\Users\\savet\\creatrbase-v2\\src\\domains\\auth\\authRoutes.js", "source_location": "L137"}, {"caller_nid": "authroutes_authroutes", "callee": "get", "source_file": "C:\\Users\\savet\\creatrbase-v2\\src\\domains\\auth\\authRoutes.js", "source_location": "L151"}, {"caller_nid": "authroutes_authroutes", "callee": "get", "source_file": "C:\\Users\\savet\\creatrbase-v2\\src\\domains\\auth\\authRoutes.js", "source_location": "L174"}, {"caller_nid": "authroutes_authroutes", "callee": "require", "source_file": "C:\\Users\\savet\\creatrbase-v2\\src\\domains\\auth\\authRoutes.js", "source_location": "L181"}, {"caller_nid": "authroutes_authroutes", "callee": "register", "source_file": "C:\\Users\\savet\\creatrbase-v2\\src\\domains\\auth\\authRoutes.js", "source_location": "L182"}, {"caller_nid": "authroutes_authroutes", "callee": "get", "source_file": "C:\\Users\\savet\\creatrbase-v2\\src\\domains\\auth\\authRoutes.js", "source_location": "L204"}, {"caller_nid": "authroutes_authroutes", "callee": "get", "source_file": "C:\\Users\\savet\\creatrbase-v2\\src\\domains\\auth\\authRoutes.js", "source_location": "L233"}]}