{"nodes": [{"id": "c_users_savet_creatrbase_v2_client_src_components_scorecard_scorecard_jsx", "label": "ScoreCard.jsx", "file_type": "code", "source_file": "C:\\Users\\savet\\creatrbase-v2\\client\\src\\components\\ScoreCard\\ScoreCard.jsx", "source_location": "L1"}, {"id": "scorecard_scorecardcontent", "label": "ScoreCardContent()", "file_type": "code", "source_file": "C:\\Users\\savet\\creatrbase-v2\\client\\src\\components\\ScoreCard\\ScoreCard.jsx", "source_location": "L18"}, {"id": "scorecard_scorecardmodal", "label": "ScoreCardModal()", "file_type": "code", "source_file": "C:\\Users\\savet\\creatrbase-v2\\client\\src\\components\\ScoreCard\\ScoreCard.jsx", "source_location": "L95"}], "edges": [{"source": "c_users_savet_creatrbase_v2_client_src_components_scorecard_scorecard_jsx", "target": "react", "relation": "imports_from", "confidence": "EXTRACTED", "source_file": "C:\\Users\\savet\\creatrbase-v2\\client\\src\\components\\ScoreCard\\ScoreCard.jsx", "source_location": "L1", "weight": 1.0}, {"source": "c_users_savet_creatrbase_v2_client_src_components_scorecard_scorecard_jsx", "target": "c_users_savet_creatrbase_v2_client_src_components_scorecard_scorecard_module_css", "relation": "imports_from", "confidence": "EXTRACTED", "source_file": "C:\\Users\\savet\\creatrbase-v2\\client\\src\\components\\ScoreCard\\ScoreCard.jsx", "source_location": "L2", "weight": 1.0}, {"source": "c_users_savet_creatrbase_v2_client_src_components_scorecard_scorecard_jsx", "target": "scorecard_scorecardcontent", "relation": "contains", "confidence": "EXTRACTED", "source_file": "C:\\Users\\savet\\creatrbase-v2\\client\\src\\components\\ScoreCard\\ScoreCard.jsx", "source_location": "L18", "weight": 1.0}, {"source": "c_users_savet_creatrbase_v2_client_src_components_scorecard_scorecard_jsx", "target": "scorecard_scorecardmodal", "relation": "contains", "confidence": "EXTRACTED", "source_file": "C:\\Users\\savet\\creatrbase-v2\\client\\src\\components\\ScoreCard\\ScoreCard.jsx", "source_location": "L95", "weight": 1.0}], "raw_calls": [{"caller_nid": "scorecard_scorecardcontent", "callee": "replace", "source_file": "C:\\Users\\savet\\creatrbase-v2\\client\\src\\components\\ScoreCard\\ScoreCard.jsx", "source_location": "L23"}, {"caller_nid": "scorecard_scorecardcontent", "callee": "join", "source_file": "C:\\Users\\savet\\creatrbase-v2\\client\\src\\components\\ScoreCard\\ScoreCard.jsx", "source_location": "L63"}, {"caller_nid": "scorecard_scorecardcontent", "callee": "filter", "source_file": "C:\\Users\\savet\\creatrbase-v2\\client\\src\\components\\ScoreCard\\ScoreCard.jsx", "source_location": "L63"}, {"caller_nid": "scorecard_scorecardcontent", "callee": "keys", "source_file": "C:\\Users\\savet\\creatrbase-v2\\client\\src\\components\\ScoreCard\\ScoreCard.jsx", "source_location": "L68"}, {"caller_nid": "scorecard_scorecardcontent", "callee": "map", "source_file": "C:\\Users\\savet\\creatrbase-v2\\client\\src\\components\\ScoreCard\\ScoreCard.jsx", "source_location": "L70"}, {"caller_nid": "scorecard_scorecardcontent", "callee": "entries", "source_file": "C:\\Users\\savet\\creatrbase-v2\\client\\src\\components\\ScoreCard\\ScoreCard.jsx", "source_location": "L70"}, {"caller_nid": "scorecard_scorecardmodal", "callee": "useRef", "source_file": "C:\\Users\\savet\\creatrbase-v2\\client\\src\\components\\ScoreCard\\ScoreCard.jsx", "source_location": "L96"}, {"caller_nid": "scorecard_scorecardmodal", "callee": "useState", "source_file": "C:\\Users\\savet\\creatrbase-v2\\client\\src\\components\\ScoreCard\\ScoreCard.jsx", "source_location": "L97"}, {"caller_nid": "scorecard_scorecardmodal", "callee": "useState", "source_file": "C:\\Users\\savet\\creatrbase-v2\\client\\src\\components\\ScoreCard\\ScoreCard.jsx", "source_location": "L98"}, {"caller_nid": "scorecard_scorecardmodal", "callee": "useState", "source_file": "C:\\Users\\savet\\creatrbase-v2\\client\\src\\components\\ScoreCard\\ScoreCard.jsx", "source_location": "L99"}]}